{
  "splitDirection": "horizontal",
  "nodeMinHeight": 16,
  "lineHeight": "1em",
  "spacingVertical": 5,
  "spacingHorizontal": 80,
  "paddingX": 8,
  "color1": "#fed766",
  "color1Thickness": "10",
  "color2": "#2ab7ca",
  "color2Thickness": "6",
  "color3": "#fe4a49",
  "color3Thickness": "4",
  "defaultColor": "#000000",
  "defaultColorThickness": "2",
  "initialExpandLevel": -1,
  "onlyUseDefaultColor": false,
  "coloring": "depth",
  "colorFreezeLevel": 0,
  "animationDuration": 500,
  "maxWidth": 0,
  "screenshotBgColor": "#039614",
  "screenshotFgColor": "#ffffff",
  "screenshotFgColorEnabled": false,
  "screenshotBgStyle": "transparent",
  "screenshotTransparentBg": true,
  "highlight": false
}